{
  "_generated": "Generated by SweetTooth, patched for charge_types support",
  "description": "Lenovo IdeaPad goodies for Gnome Shell\n\nPatched to prefer the Linux power_supply charge_types interface for battery conservation mode, with legacy conservation_mode fallback.",
  "gettext-domain": "ideapad",
  "name": "IdeaPad",
  "shell-version": [
    "45",
    "46",
    "47",
    "48",
    "49",
    "50"
  ],
  "url": "https://github.com/christiandoxa/vantage",
  "uuid": "ideapad@laurento.frittella",
  "version": 23
}
